mono-stubs/__init__.pyi
mono-stubs/py.typed
mono-stubs/model/__init__.pyi
mono-stubs/model/monodepth_model.pyi
mono-stubs/model/model_pipelines/__base_model__.pyi
mono-stubs/model/model_pipelines/__init__.pyi
mono_stubs-0.0.3.dist-info/METADATA
mono_stubs-0.0.3.dist-info/WHEEL
mono_stubs-0.0.3.dist-info/licenses/LICENSE
mono_stubs-0.0.3.dist-info/RECORD
